rika/__init__.py
rika/rika.py
rika-0.1.0.dist-info/AUTHORS.rst
rika-0.1.0.dist-info/LICENSE
rika-0.1.0.dist-info/METADATA
rika-0.1.0.dist-info/WHEEL
rika-0.1.0.dist-info/top_level.txt
rika-0.1.0.dist-info/RECORD
