Metadata-Version: 2.1
Name: rika
Version: 0.1.0
Summary: This is a python library that make it easy to use technical analysis stock market in China.
Home-page: https://github.com/lvzhi/rika
Author: Lv Zhi
Author-email: 279094354@qq.com
License: MIT license
Keywords: rika
Platform: UNKNOWN
Classifier: Development Status :: 2 - Pre-Alpha
Classifier: Intended Audience :: Developers
Classifier: License :: OSI Approved :: MIT License
Classifier: Programming Language :: Python :: 3.6
Classifier: Programming Language :: Python :: 3.7
